math1/__init__.py
math1/math_add_test.py
math2/__init__.py
math2/math_minus_test.py
hellomath101-0.0.5.dist-info/LICENSE.txt
hellomath101-0.0.5.dist-info/METADATA
hellomath101-0.0.5.dist-info/WHEEL
hellomath101-0.0.5.dist-info/top_level.txt
hellomath101-0.0.5.dist-info/RECORD
