Metadata-Version: 2.1
Name: hellomath101
Version: 0.0.5
Summary: short package description
Home-page: https://github.com/gmyrianthous/example-publish-pypi
Author: Tester
Author-email: email@example.com
License: MIT
Keywords: example documentation tutorial
Classifier: Development Status :: 3 - Alpha
Classifier: Topic :: Utilities
Classifier: License :: OSI Approved :: BSD License
Requires-Python: >=3.6
License-File: LICENSE.txt
